napari_workshop_browser/__init__.py
napari_workshop_browser/_widget.py
napari_workshop_browser/napari.yaml
napari_workshop_browser/_tests/__init__.py
napari_workshop_browser/_tests/test_widget.py
napari_workshop_browser-0.0.3.dist-info/LICENSE
napari_workshop_browser-0.0.3.dist-info/METADATA
napari_workshop_browser-0.0.3.dist-info/WHEEL
napari_workshop_browser-0.0.3.dist-info/entry_points.txt
napari_workshop_browser-0.0.3.dist-info/top_level.txt
napari_workshop_browser-0.0.3.dist-info/RECORD
