Metadata-Version: 2.1
Name: napari-workshop-browser
Version: 0.0.3
Summary: A plugin to browse and follow napari workshops
Home-page: https://github.com/kephale/napari-workshop-browser
Author: Kyle Harrington
Author-email: napari@kyleharrington.com
License: BSD-3-Clause
Project-URL: Bug Tracker, https://github.com/kephale/napari-workshop-browser/issues
Project-URL: Documentation, https://github.com/kephale/napari-workshop-browser#README.md
Project-URL: Source Code, https://github.com/kephale/napari-workshop-browser
Project-URL: User Support, https://github.com/kephale/napari-workshop-browser/issues
Classifier: Development Status :: 2 - Pre-Alpha
Classifier: Framework :: napari
Classifier: Intended Audience :: Developers
Classifier: License :: OSI Approved :: BSD License
Classifier: Operating System :: OS Independent
Classifier: Programming Language :: Python
Classifier: Programming Language :: Python :: 3
Classifier: Programming Language :: Python :: 3 :: Only
Classifier: Programming Language :: Python :: 3.8
Classifier: Programming Language :: Python :: 3.9
Classifier: Programming Language :: Python :: 3.10
Classifier: Topic :: Scientific/Engineering :: Image Processing
Requires-Python: >=3.8
License-File: LICENSE
Requires-Dist: numpy
Requires-Dist: superqt
Requires-Dist: qtpy
Requires-Dist: notebook <7.0.0
Requires-Dist: jupytext
Requires-Dist: napari
Requires-Dist: appdirs
Requires-Dist: requests
Provides-Extra: testing
Requires-Dist: tox ; extra == 'testing'
Requires-Dist: pytest ; extra == 'testing'
Requires-Dist: pytest-cov ; extra == 'testing'
Requires-Dist: pytest-qt ; extra == 'testing'
Requires-Dist: napari ; extra == 'testing'
Requires-Dist: pyqt5 ; extra == 'testing'
